{
  "assistant": {
    "name": "Assistant",
    "name_plural": "Assistants",
    "icon": {
      "class": "fas fa-microphone-lines"
    }
  },

  "battery": {
    "name": "Battery",
    "name_plural": "Batteries",
    "icon": {
      "class": "fas fa-battery-full"
    }
  },

  "button": {
    "name": "Button",
    "name_plural": "Buttons",
    "icon": {
      "class": "fas fa-circle-dot"
    }
  },

  "cpu_info": {
    "name": "System",
    "name_plural": "System",
    "icon": {
      "class": "fas fa-circle-info"
    }
  },

  "cpu_stats": {
    "name": "System",
    "name_plural": "System",
    "icon": {
      "class": "fas fa-gauge"
    }
  },

  "cpu_times": {
    "name": "System",
    "name_plural": "System",
    "icon": {
      "class": "fas fa-clock"
    }
  },

  "memory_stats": {
    "name": "System",
    "name_plural": "System",
    "icon": {
      "class": "fas fa-memory"
    }
  },

  "swap_stats": {
    "name": "System",
    "name_plural": "System",
    "icon": {
      "class": "fas fa-memory"
    }
  },

  "disk": {
    "name": "System",
    "name_plural": "System",
    "icon": {
      "class": "fas fa-hard-drive"
    }
  },

  "network_interface": {
    "name": "System",
    "name_plural": "System",
    "icon": {
      "class": "fas fa-ethernet"
    }
  },

  "system_temperature": {
    "name": "System",
    "name_plural": "System",
    "icon": {
      "class": "fas fa-temperature-half"
    }
  },

  "system_fan": {
    "name": "System",
    "name_plural": "System",
    "icon": {
      "class": "fas fa-fan"
    }
  },

  "system_battery": {
    "name": "System",
    "name_plural": "System",
    "icon": {
      "class": "fas fa-battery-full"
    }
  },

  "current_sensor": {
    "name": "Sensor",
    "name_plural": "Sensors",
    "icon": {
      "class": "fas fa-bolt"
    }
  },

  "cpu": {
    "name": "System",
    "name_plural": "System",
    "icon": {
      "class": "fas fa-microchip"
    }
  },

  "motion_sensor": {
    "name": "Sensor",
    "name_plural": "Sensors",
    "icon": {
      "class": "fas fa-person-running"
    }
  },

  "distance_sensor": {
    "name": "Sensor",
    "name_plural": "Sensors",
    "icon": {
      "class": "fas fa-ruler-horizontal"
    }
  },

  "bluetooth_device": {
    "name": "Device",
    "name_plural": "Devices",
    "icon": {
      "class": "fab fa-bluetooth-b"
    }
  },

  "cloud_instance": {
    "name": "Cloud Entity",
    "name_plural": "Cloud Entities",
    "icon": {
      "class": "fas fa-cloud"
    }
  },

  "bluetooth_service": {
    "name": "Service",
    "name_plural": "Services",
    "icon": {
      "class": "fas fa-satellite-dish"
    }
  },

  "accelerometer": {
    "name": "Sensor",
    "name_plural": "Sensors",
    "icon": {
      "class": "fas fa-up-down-left-right"
    }
  },

  "magnetometer": {
    "name": "Sensor",
    "name_plural": "Sensors",
    "icon": {
      "class": "fas fa-magnet"
    }
  },

  "device": {
    "name": "Device",
    "name_plural": "Devices",
    "icon": {
      "class": "fas fa-gear"
    }
  },

  "volume": {
    "name": "Dimmer",
    "name_plural": "Dimmers",
    "icon": {
      "class": "fas fa-volume-high"
    }
  },

  "dimmer": {
    "name": "Dimmer",
    "name_plural": "Dimmers",
    "icon": {
      "class": "fas fa-gauge"
    }
  },

  "energy_sensor": {
    "name": "Sensor",
    "name_plural": "Sensors",
    "icon": {
      "class": "fas fa-plug"
    }
  },

  "entity": {
    "name": "Entity",
    "name_plural": "Entities",
    "icon": {
      "class": "fas fa-circle-question"
    }
  },

  "humidity_sensor": {
    "name": "Sensor",
    "name_plural": "Sensors",
    "icon": {
      "class": "fas fa-droplet"
    }
  },

  "dew_point_sensor": {
    "name": "Sensor",
    "name_plural": "Sensors",
    "icon": {
      "class": "fas fa-hand-holding-droplet"
    }
  },

  "illuminance_sensor": {
    "name": "Sensor",
    "name_plural": "Sensors",
    "icon": {
      "class": "fas fa-sun"
    }
  },

  "light": {
    "name": "Light",
    "name_plural": "Lights",
    "icon": {
      "class": "fas fa-lightbulb"
    }
  },

  "contact_sensor": {
    "name": "Sensor",
    "name_plural": "Sensors",
    "icon": {
      "class": "far fa-hand"
    }
  },

  "presence_sensor": {
    "name": "Sensor",
    "name_plural": "Sensors",
    "icon": {
      "class": "fas fa-person"
    }
  },

  "weight_sensor": {
    "name": "Sensor",
    "name_plural": "Sensors",
    "icon": {
      "class": "fas fa-weight-scale"
    }
  },

  "link_quality": {
    "name": "Link Quality",
    "name_plural": "Link Qualities",
    "icon": {
      "class": "fas fa-tower-broadcast"
    }
  },

  "power_sensor": {
    "name": "Sensor",
    "name_plural": "Sensors",
    "icon": {
      "class": "fas fa-plug"
    }
  },

  "temperature_sensor": {
    "name": "Sensor",
    "name_plural": "Sensors",
    "icon": {
      "class": "fas fa-temperature-half"
    }
  },

  "steps_sensor": {
    "name": "Sensor",
    "name_plural": "Sensors",
    "icon": {
      "class": "fas fa-shoe-prints"
    }
  },

  "heart_rate_sensor": {
    "name": "Sensor",
    "name_plural": "Sensors",
    "icon": {
      "class": "fas fa-heart-pulse"
    }
  },

  "time_duration_sensor": {
    "name": "Sensor",
    "name_plural": "Sensors",
    "icon": {
      "class": "fas fa-clock"
    }
  },

  "pressure_sensor": {
    "name": "Sensor",
    "name_plural": "Sensors",
    "icon": {
      "class": "fas fa-gauge"
    }
  },

  "muted": {
    "name": "Switch",
    "name_plural": "Switches",
    "icon": {
      "class": "fas fa-volume-xmark"
    }
  },

  "enum_switch": {
    "name": "Switch",
    "name_plural": "Switches",
    "icon": {
      "class": "fas fa-gauge"
    }
  },

  "switch": {
    "name": "Switch",
    "name_plural": "Switches",
    "icon": {
      "class": "fas fa-toggle-on"
    }
  },

  "variable": {
    "name": "Variable",
    "name_plural": "Variables",
    "icon": {
      "class": "fas fa-square-root-variable"
    }
  },

  "voltage_sensor": {
    "name": "Sensor",
    "name_plural": "Sensors",
    "icon": {
      "class": "fas fa-car-battery"
    }
  },

  "composite_sensor": {
    "name": "Sensor",
    "name_plural": "Sensors",
    "icon": {
      "class": "fas fa-thermometer"
    }
  },

  "binary_sensor": {
    "name": "Sensor",
    "name_plural": "Sensors",
    "icon": {
      "class": "fas fa-thermometer"
    }
  },

  "numeric_sensor": {
    "name": "Sensor",
    "name_plural": "Sensors",
    "icon": {
      "class": "fas fa-thermometer"
    }
  },

  "percent_sensor": {
    "name": "Sensor",
    "name_plural": "Sensors",
    "icon": {
      "class": "fas fa-thermometer"
    }
  },

  "enum_sensor": {
    "name": "Sensor",
    "name_plural": "Sensors",
    "icon": {
      "class": "fas fa-thermometer"
    }
  },

  "raw_sensor": {
    "name": "Sensor",
    "name_plural": "Sensors",
    "icon": {
      "class": "fas fa-thermometer"
    }
  },

  "sensor": {
    "name": "Sensor",
    "name_plural": "Sensors",
    "icon": {
      "class": "fas fa-thermometer"
    }
  }
}
