{
  "icons": {
    "camera.android.ipcam": {
      "class": "fab fa-android"
    },
    "camera.cv": {
      "class": "fas fa-camera"
    },
    "camera.ffmpeg": {
      "class": "fas fa-camera"
    },
    "camera.gstreamer": {
      "class": "fas fa-camera"
    },
    "camera.ir.mlx90640": {
      "class": "fas fa-sun"
    },
    "camera.pi": {
      "class": "fas fa-camera"
    },
    "light.hue": {
      "class": "fas fa-lightbulb"
    },
    "media.omxplayer": {
      "class": "fa fa-film"
    },
    "media.mplayer": {
      "class": "fa fa-film"
    },
    "media.mpv": {
      "class": "fa fa-film"
    },
    "media.vlc": {
      "class": "fa fa-film"
    },
    "music.mpd": {
      "class": "fas fa-music"
    },
    "music.snapcast": {
      "class": "fa fa-volume-up"
    },
    "torrent": {
      "class": "fa fa-magnet"
    },
    "rtorrent": {
      "class": "fa fa-magnet"
    },
    "switches": {
      "class": "fas fa-toggle-on"
    },
    "sound": {
      "class": "fa fa-microphone"
    },
    "tts": {
      "class": "far fa-comment"
    },
    "tts.google": {
      "class": "fas fa-comment"
    },
    "zigbee.mqtt": {
      "imgUrl": "/icons/zigbee.svg"
    },
    "zwave": {
      "imgUrl": "/icons/z-wave.png"
    }
  }
}
